mavehgvs/__init__.py
mavehgvs/exceptions.py
mavehgvs/position.py
mavehgvs/py.typed
mavehgvs/util.py
mavehgvs/variant.py
mavehgvs/patterns/__init__.py
mavehgvs/patterns/combined.py
mavehgvs/patterns/dna.py
mavehgvs/patterns/position.py
mavehgvs/patterns/protein.py
mavehgvs/patterns/rna.py
mavehgvs/patterns/util.py
mavehgvs-0.7.0.dist-info/METADATA
mavehgvs-0.7.0.dist-info/WHEEL
mavehgvs-0.7.0.dist-info/licenses/LICENSE
mavehgvs-0.7.0.dist-info/RECORD
