Metadata-Version: 2.4
Name: mavehgvs
Version: 0.7.0
Summary: Regular expression-based validation of HGVS-style variant strings for Multiplexed Assays of Variant Effect.
Project-URL: repository, https://github.com/VariantEffect/mavehgvs
Project-URL: documentation, https://www.mavedb.org/docs/mavehgvs
Author-email: Alan F Rubin <alan.rubin@wehi.edu.au>
License-Expression: BSD-3-Clause
License-File: LICENSE
Classifier: Development Status :: 3 - Alpha
Classifier: Intended Audience :: Science/Research
Classifier: License :: OSI Approved :: BSD License
Classifier: Operating System :: OS Independent
Classifier: Programming Language :: Python :: 3
Classifier: Topic :: Scientific/Engineering :: Bio-Informatics
Requires-Python: >=3.6
Requires-Dist: fqfa>=1.2.3
Provides-Extra: dev
Requires-Dist: black; extra == 'dev'
Requires-Dist: flake8; extra == 'dev'
Requires-Dist: pre-commit; extra == 'dev'
Requires-Dist: pytest; extra == 'dev'
